sample/__init__.py
sample/functions.py
sample/main.py
pypi_slava-0.0.17.dist-info/LICENSE
pypi_slava-0.0.17.dist-info/METADATA
pypi_slava-0.0.17.dist-info/WHEEL
pypi_slava-0.0.17.dist-info/entry_points.txt
pypi_slava-0.0.17.dist-info/top_level.txt
pypi_slava-0.0.17.dist-info/RECORD
