Metadata-Version: 2.1
Name: pypi-slava
Version: 0.0.17
Summary: test tool
Home-page: https://github.com/vshneidmiller/pypi
Author: Viacheslav Shneidmillier
Author-email: v.shneidmiller@gmail.com
Classifier: Programming Language :: Python :: 3
Classifier: License :: OSI Approved :: MIT License
Classifier: Operating System :: OS Independent
Requires-Python: >=3.6
License-File: LICENSE
